atomic_bomb_engine-0.42.0.dist-info/METADATA
atomic_bomb_engine-0.42.0.dist-info/WHEEL
atomic_bomb_engine-0.42.0.dist-info/licenses/LICENSE
atomic_bomb_engine.libs/libcrypto-524aa652.so.3
atomic_bomb_engine.libs/libgcc_s-0cd532bd.so.1
atomic_bomb_engine.libs/libssl-c8b6d196.so.3
atomic_bomb_engine/__init__.py
atomic_bomb_engine/__init__.pyi
atomic_bomb_engine/atomic_bomb_engine.cpython-311-x86_64-linux-musl.so
atomic_bomb_engine/dist/.gitkeep
atomic_bomb_engine/middleware.py
atomic_bomb_engine/server.py
atomic_bomb_engine-0.42.0.dist-info/RECORD
