Metadata-Version: 2.4
Name: atomic_bomb_engine
Version: 0.42.0
Classifier: Programming Language :: Python :: 3
Classifier: Programming Language :: Python :: 3.9
Classifier: Programming Language :: Python :: 3.10
Classifier: Programming Language :: Python :: 3.11
Classifier: Programming Language :: Python :: 3.12
Classifier: Programming Language :: Python :: 3.13
Classifier: Programming Language :: Rust
Classifier: Operating System :: OS Independent
Requires-Dist: aiohttp
Requires-Dist: aiosqlite
Summary: 使用rust开发的高性能python压测工具
Keywords: rust,python,binding
Author-email: qyzhg <qyzhg@qyzhg.com>
Requires-Python: >=3.8
